{
 "te-us-stock-market": {
  "title": "US Stock Market",
  "lines": [
   "1. 반도체 기업의 대량 매도로 미국 주요 주가지수가 사상 최고치에서 후퇴하며 하락 마감했다.",
   "2. AI 초대형 기업의 과도한 인프라 투자 타당성에 대한 의구심과 중국 딥시크의 AI 칩 개발 보도로 대부분 반도체주가 하락했고 삼성전자의 19배 분기 이익 급증도 시장 심리에 영향을 미치지 못했으며 엔비디아만 소폭 상승했다.",
   "3. 호르무즈 해협 유조선 공격으로 에너지 인플레이션 우려가 커지며 국채 금리가 상승한 점이 전반 시장에 부담으로 작용해 비자, 캐터필러 등도 동반 하락했다."
  ],
  "ts": "07-08 07:53"
 },
 "te-natural-gas": {
  "title": "Natural Gas (TE)",
  "lines": [
   "미국 천연가스 선물 가격이 1주일 만에 최고치인 MMBtu당 3.28달러까지 상승했으며, 48개 주 생산량 감소와 LNG 수출 플랜트 가스 유입 증가가 주요 상승 배경으로 작용했다.",
   "한편 최근 폭염으로 발전소가 증가한 냉방 수요 대응을 위해 전력 생산을 확대하면서 가스 수요가 급증해 국내 저장고에서의 가스 감출이 이뤄져 가격에 추가 상승 압력을 가했다.",
   "다만 7월 15일까지 미국 동부 지역에 시원한 날씨가 이어질 것이라는 기상 전망이 나오면서 냉방 수요 감소 우려가 커져 향후 가격 상승은 제한될 것으로 전망된다."
  ],
  "ts": "07-08 07:53"
 },
 "te-gold": {
  "title": "Gold",
  "lines": [
   "We",
   "need to",
   "summarize the",
   "given text"
  ],
  "ts": "07-08 07:53"
 },
 "te-us-bond-yield": {
  "title": "US 10Y Bond Yield",
  "lines": [
   "미국 국채 금리가 한 달 만에 최고 수준으로 상승하며 유가 급등이 인플레이션 우려를 자극함.",
   "중동 호르무즈 해협에서 LNG 운반선 피격으로 유가가 2% 이상 오르며 글로벌 에너지 공급 불안이 확대됨.",
   "유가 반등으로 연준의 9월 금리 인상 가능성이 58%로 소폭 상승했고, 시장은 수요일 공개될 FOMC 의사록을 주목하고 있음."
  ],
  "ts": "07-08 07:53"
 }
}