{
 "te-us-stock-market": {
  "title": "US Stock Market",
  "lines": [
   "석유가격 급등·빅테크 실적 부진으로 시장 급락 후, 미국 선물은 변동 없이 안정세.",
   "브렌트유는 사우디 유조선 공격 소식에 100달러를 넘어 중동 공급 우려가 커졌다.",
   "테슬라 15% 급락·알파벳 7% 하락, 나스닥이 주간 하락을 주도했다."
  ],
  "ts": "07-24 18:17"
 },
 "te-natural-gas": {
  "title": "Natural Gas (TE)",
  "lines": [
   "미국 천연가스 선물, 공급 충분·LNG 수출 감소로 $2.90 이하",
   "재고 32bcf 증가·5년 평균 초과, 재고량 6.4% 시즌 평균 위",
   "온난한 날씨 예보로 전력 수요↑, 가격 일부 회복 기대"
  ],
  "ts": "07-24 18:17"
 },
 "te-gold": {
  "title": "Gold",
  "lines": [
   "금값이 온스당 4,030달러까지 하락, 중동 갈등으로 유가 급등, 연준 긴축 기대 상승",
   "트럼프, 이란 군사 확대 경고·후티 공격 테헤란 책임 추궁, 브렌트유 100달러 돌파",
   "유가 상승·인플레이션 우려로 연준 금리 인상 기대↑, 관세 확대, 금은 소폭 상승."
  ],
  "ts": "07-24 18:17"
 },
 "te-us-bond-yield": {
  "title": "US 10Y Bond Yield",
  "lines": [
   "미국 10년 국채 수익률 4.70%까지 상승, 5일 연속, 2025년 1월 이후 최고.",
   "멕·캐·영·인 등 10% 관세, EU·대만 10%, 일본·한국·스위스 12.5% 부과.",
   "중동 긴장·강한 고용시장으로 에너지 가격 상승, 연준 금리 인상 기대감 확대."
  ],
  "ts": "07-24 18:17"
 }
}